{
  "$schema": "https://json-schema.org/draft/2020-12/schema",
  "$id": "https://catalog.lintel.tools/schemas/schemastore/_shared/mlos-config-mlos-jsonc-mlos-json5-mlos-json--service-schema--mock-fileshare-service-subschema.json",
  "title": "mlos_bench Mock FileShare Service config",
  "description": "config for an mlos_bench Mock FileShare Service",
  "type": "object",
  "properties": {
    "class": {
      "enum": [
        "mlos_bench.tests.services.remote.mock.mock_fileshare_service.MockFileShareService"
      ]
    },
    "config": {
      "properties": {
        "fileShareName": {
          "type": "string"
        }
      },
      "required": [
        "fileShareName"
      ],
      "unevaluatedProperties": false
    }
  },
  "required": [
    "class",
    "config"
  ]
}
