{
  "$schema": "https://json-schema.org/draft/2020-12/schema",
  "$id": "https://catalog.lintel.tools/schemas/schemastore/serverless-framework-configuration/_shared/latest--aws-groundstation-config.json",
  "title": "AWSGroundStationConfigProperties",
  "description": "AWS Ground Station config resource type for CloudFormation.. Source:- <https://github.com/aws-cloudformation/aws-cloudformation-resource-providers-ground-station.git>",
  "x-lintel": {
    "source": "https://raw.githubusercontent.com/lalcebo/json-schema/master/serverless/resources/cloudformation-modified/aws-groundstation-config.json",
    "sourceSha256": "26a9d23d3f4e4c2c7077c550fd760296b9a0fe97014cf86536f8f1861bab81f4",
    "invalid": true
  },
  "type": "object",
  "properties": {
    "Name": {
      "oneOf": [
        {
          "type": "string",
          "pattern": "^[ a-zA-Z0-9_:-]{1,256}$"
        },
        {
          "$ref": "https://catalog.lintel.tools/schemas/schemastore/serverless-framework-configuration/_shared/latest--cf.functions.json#/Aws_CF_FunctionString"
        }
      ]
    },
    "Tags": {
      "type": "array",
      "items": {
        "$ref": "#/$defs/Tag"
      }
    },
    "ConfigData": {
      "$ref": "#/$defs/ConfigData"
    }
  },
  "typeName": "AWS::GroundStation::Config",
  "additionalProperties": false,
  "sourceUrl": "https://github.com/aws-cloudformation/aws-cloudformation-resource-providers-ground-station.git",
  "$defs": {
    "JsonString": {
      "oneOf": [
        {
          "type": "string",
          "pattern": "^[{}\\[\\]:.,\"0-9A-z\\-_\\s]{1,8192}$"
        },
        {
          "$ref": "https://catalog.lintel.tools/schemas/schemastore/serverless-framework-configuration/_shared/latest--cf.functions.json#/Aws_CF_FunctionString"
        }
      ],
      "title": "AWSGroundStationConfigJsonStringDefinition"
    },
    "ConfigData": {
      "type": "object",
      "minProperties": 1,
      "maxProperties": 1,
      "properties": {
        "AntennaDownlinkConfig": {
          "$ref": "#/$defs/AntennaDownlinkConfig"
        },
        "TrackingConfig": {
          "$ref": "#/$defs/TrackingConfig"
        },
        "DataflowEndpointConfig": {
          "$ref": "#/$defs/DataflowEndpointConfig"
        },
        "AntennaDownlinkDemodDecodeConfig": {
          "$ref": "#/$defs/AntennaDownlinkDemodDecodeConfig"
        },
        "AntennaUplinkConfig": {
          "$ref": "#/$defs/AntennaUplinkConfig"
        },
        "UplinkEchoConfig": {
          "$ref": "#/$defs/UplinkEchoConfig"
        },
        "S3RecordingConfig": {
          "$ref": "#/$defs/S3RecordingConfig"
        }
      },
      "additionalProperties": false,
      "title": "AWSGroundStationConfigConfigDataDefinition"
    },
    "EirpUnits": {
      "oneOf": [
        {
          "type": "string",
          "enum": [
            "dBW"
          ]
        },
        {
          "$ref": "https://catalog.lintel.tools/schemas/schemastore/serverless-framework-configuration/_shared/latest--cf.functions.json#/Aws_CF_FunctionString"
        }
      ],
      "title": "AWSGroundStationConfigEirpUnitsDefinition"
    },
    "Eirp": {
      "type": "object",
      "properties": {
        "Value": {
          "type": "number"
        },
        "Units": {
          "$ref": "#/$defs/EirpUnits"
        }
      },
      "additionalProperties": false,
      "title": "AWSGroundStationConfigEirpDefinition"
    },
    "FrequencyUnits": {
      "oneOf": [
        {
          "type": "string",
          "enum": [
            "GHz",
            "MHz",
            "kHz"
          ]
        },
        {
          "$ref": "https://catalog.lintel.tools/schemas/schemastore/serverless-framework-configuration/_shared/latest--cf.functions.json#/Aws_CF_FunctionString"
        }
      ],
      "title": "AWSGroundStationConfigFrequencyUnitsDefinition"
    },
    "BandwidthUnits": {
      "oneOf": [
        {
          "type": "string",
          "enum": [
            "GHz",
            "MHz",
            "kHz"
          ]
        },
        {
          "$ref": "https://catalog.lintel.tools/schemas/schemastore/serverless-framework-configuration/_shared/latest--cf.functions.json#/Aws_CF_FunctionString"
        }
      ],
      "title": "AWSGroundStationConfigBandwidthUnitsDefinition"
    },
    "FrequencyBandwidth": {
      "type": "object",
      "properties": {
        "Value": {
          "type": "number"
        },
        "Units": {
          "$ref": "#/$defs/BandwidthUnits"
        }
      },
      "additionalProperties": false,
      "title": "AWSGroundStationConfigFrequencyBandwidthDefinition"
    },
    "Frequency": {
      "type": "object",
      "properties": {
        "Value": {
          "type": "number"
        },
        "Units": {
          "$ref": "#/$defs/FrequencyUnits"
        }
      },
      "additionalProperties": false,
      "title": "AWSGroundStationConfigFrequencyDefinition"
    },
    "Polarization": {
      "oneOf": [
        {
          "type": "string",
          "enum": [
            "LEFT_HAND",
            "RIGHT_HAND",
            "NONE"
          ]
        },
        {
          "$ref": "https://catalog.lintel.tools/schemas/schemastore/serverless-framework-configuration/_shared/latest--cf.functions.json#/Aws_CF_FunctionString"
        }
      ],
      "title": "AWSGroundStationConfigPolarizationDefinition"
    },
    "S3KeyPrefix": {
      "oneOf": [
        {
          "type": "string",
          "pattern": "^([a-zA-Z0-9_\\-=/]|\\{satellite_id\\}|\\{config\\-name\\}|\\{s3\\-config-id\\}|\\{year\\}|\\{month\\}|\\{day\\}){1,900}$"
        },
        {
          "$ref": "https://catalog.lintel.tools/schemas/schemastore/serverless-framework-configuration/_shared/latest--cf.functions.json#/Aws_CF_FunctionString"
        }
      ],
      "title": "AWSGroundStationConfigS3KeyPrefixDefinition"
    },
    "BucketArn": {
      "oneOf": [
        {
          "type": "string"
        },
        {
          "$ref": "https://catalog.lintel.tools/schemas/schemastore/serverless-framework-configuration/_shared/latest--cf.functions.json#/Aws_CF_FunctionString"
        }
      ],
      "title": "AWSGroundStationConfigBucketArnDefinition"
    },
    "RoleArn": {
      "oneOf": [
        {
          "type": "string"
        },
        {
          "$ref": "https://catalog.lintel.tools/schemas/schemastore/serverless-framework-configuration/_shared/latest--cf.functions.json#/Aws_CF_FunctionString"
        }
      ],
      "title": "AWSGroundStationConfigRoleArnDefinition"
    },
    "UplinkSpectrumConfig": {
      "type": "object",
      "properties": {
        "CenterFrequency": {
          "$ref": "#/$defs/Frequency"
        },
        "Polarization": {
          "$ref": "#/$defs/Polarization"
        }
      },
      "additionalProperties": false,
      "title": "AWSGroundStationConfigUplinkSpectrumConfigDefinition"
    },
    "SpectrumConfig": {
      "type": "object",
      "properties": {
        "CenterFrequency": {
          "$ref": "#/$defs/Frequency"
        },
        "Bandwidth": {
          "$ref": "#/$defs/FrequencyBandwidth"
        },
        "Polarization": {
          "$ref": "#/$defs/Polarization"
        }
      },
      "additionalProperties": false,
      "title": "AWSGroundStationConfigSpectrumConfigDefinition"
    },
    "AntennaDownlinkConfig": {
      "type": "object",
      "properties": {
        "SpectrumConfig": {
          "$ref": "#/$defs/SpectrumConfig"
        }
      },
      "additionalProperties": false,
      "title": "AWSGroundStationConfigAntennaDownlinkConfigDefinition"
    },
    "TrackingConfig": {
      "type": "object",
      "properties": {
        "Autotrack": {
          "oneOf": [
            {
              "type": "string",
              "enum": [
                "REQUIRED",
                "PREFERRED",
                "REMOVED"
              ]
            },
            {
              "$ref": "https://catalog.lintel.tools/schemas/schemastore/serverless-framework-configuration/_shared/latest--cf.functions.json#/Aws_CF_FunctionString"
            }
          ]
        }
      },
      "additionalProperties": false,
      "title": "AWSGroundStationConfigTrackingConfigDefinition"
    },
    "DataflowEndpointConfig": {
      "type": "object",
      "properties": {
        "DataflowEndpointName": {
          "oneOf": [
            {
              "type": "string"
            },
            {
              "$ref": "https://catalog.lintel.tools/schemas/schemastore/serverless-framework-configuration/_shared/latest--cf.functions.json#/Aws_CF_FunctionString"
            }
          ]
        },
        "DataflowEndpointRegion": {
          "oneOf": [
            {
              "type": "string"
            },
            {
              "$ref": "https://catalog.lintel.tools/schemas/schemastore/serverless-framework-configuration/_shared/latest--cf.functions.json#/Aws_CF_FunctionString"
            }
          ]
        }
      },
      "additionalProperties": false,
      "title": "AWSGroundStationConfigDataflowEndpointConfigDefinition"
    },
    "DemodulationConfig": {
      "type": "object",
      "properties": {
        "UnvalidatedJSON": {
          "$ref": "#/$defs/JsonString"
        }
      },
      "additionalProperties": false,
      "title": "AWSGroundStationConfigDemodulationConfigDefinition"
    },
    "DecodeConfig": {
      "type": "object",
      "properties": {
        "UnvalidatedJSON": {
          "$ref": "#/$defs/JsonString"
        }
      },
      "additionalProperties": false,
      "title": "AWSGroundStationConfigDecodeConfigDefinition"
    },
    "AntennaDownlinkDemodDecodeConfig": {
      "type": "object",
      "properties": {
        "SpectrumConfig": {
          "$ref": "#/$defs/SpectrumConfig"
        },
        "DemodulationConfig": {
          "$ref": "#/$defs/DemodulationConfig"
        },
        "DecodeConfig": {
          "$ref": "#/$defs/DecodeConfig"
        }
      },
      "additionalProperties": false,
      "title": "AWSGroundStationConfigAntennaDownlinkDemodDecodeConfigDefinition"
    },
    "AntennaUplinkConfig": {
      "type": "object",
      "properties": {
        "SpectrumConfig": {
          "$ref": "#/$defs/UplinkSpectrumConfig"
        },
        "TargetEirp": {
          "$ref": "#/$defs/Eirp"
        },
        "TransmitDisabled": {
          "type": "boolean"
        }
      },
      "additionalProperties": false,
      "title": "AWSGroundStationConfigAntennaUplinkConfigDefinition"
    },
    "UplinkEchoConfig": {
      "type": "object",
      "properties": {
        "Enabled": {
          "type": "boolean"
        },
        "AntennaUplinkConfigArn": {
          "oneOf": [
            {
              "type": "string"
            },
            {
              "$ref": "https://catalog.lintel.tools/schemas/schemastore/serverless-framework-configuration/_shared/latest--cf.functions.json#/Aws_CF_FunctionString"
            }
          ]
        }
      },
      "additionalProperties": false,
      "title": "AWSGroundStationConfigUplinkEchoConfigDefinition"
    },
    "S3RecordingConfig": {
      "type": "object",
      "properties": {
        "BucketArn": {
          "$ref": "#/$defs/BucketArn"
        },
        "RoleArn": {
          "$ref": "#/$defs/RoleArn"
        },
        "Prefix": {
          "$ref": "#/$defs/S3KeyPrefix"
        }
      },
      "additionalProperties": false,
      "title": "AWSGroundStationConfigS3RecordingConfigDefinition"
    },
    "Tag": {
      "type": "object",
      "properties": {
        "Key": {
          "oneOf": [
            {
              "type": "string",
              "pattern": "^[ a-zA-Z0-9\\+\\-=._:/@]{1,128}$"
            },
            {
              "$ref": "https://catalog.lintel.tools/schemas/schemastore/serverless-framework-configuration/_shared/latest--cf.functions.json#/Aws_CF_FunctionString"
            }
          ]
        },
        "Value": {
          "oneOf": [
            {
              "type": "string",
              "pattern": "^[ a-zA-Z0-9\\+\\-=._:/@]{1,256}$"
            },
            {
              "$ref": "https://catalog.lintel.tools/schemas/schemastore/serverless-framework-configuration/_shared/latest--cf.functions.json#/Aws_CF_FunctionString"
            }
          ]
        }
      },
      "additionalProperties": false,
      "title": "AWSGroundStationConfigTagDefinition"
    }
  },
  "primaryIdentifier": [
    "/properties/Arn"
  ],
  "required": [
    "Name",
    "ConfigData"
  ],
  "readOnlyProperties": [
    "/properties/Arn",
    "/properties/Id",
    "/properties/Type"
  ]
}
