{
  "$schema": "https://json-schema.org/draft/2020-12/schema",
  "$id": "https://catalog.lintel.tools/schemas/schemastore/serverless-framework-configuration/_shared/latest--aws-kinesisanalytics-applicationoutput.json",
  "title": "AWSKinesisAnalyticsApplicationOutputProperties",
  "description": "Resource Type definition for AWS::KinesisAnalytics::ApplicationOutput. Source:- No source definition found, add manually please",
  "x-lintel": {
    "source": "https://raw.githubusercontent.com/lalcebo/json-schema/master/serverless/resources/cloudformation-modified/aws-kinesisanalytics-applicationoutput.json",
    "sourceSha256": "9688cf0c7c547d8c00213f93505c16ccbf54e068b2961ee6aa7024089c510093",
    "invalid": true
  },
  "type": "object",
  "properties": {
    "ApplicationName": {
      "oneOf": [
        {
          "type": "string"
        },
        {
          "$ref": "https://catalog.lintel.tools/schemas/schemastore/serverless-framework-configuration/_shared/latest--cf.functions.json#/Aws_CF_FunctionString"
        }
      ]
    },
    "Output": {
      "$ref": "#/$defs/Output"
    }
  },
  "typeName": "AWS::KinesisAnalytics::ApplicationOutput",
  "readOnlyProperties": [
    "/properties/Id"
  ],
  "additionalProperties": false,
  "primaryIdentifier": [
    "/properties/Id"
  ],
  "$defs": {
    "Output": {
      "type": "object",
      "additionalProperties": false,
      "properties": {
        "DestinationSchema": {
          "$ref": "#/$defs/DestinationSchema"
        },
        "LambdaOutput": {
          "$ref": "#/$defs/LambdaOutput"
        },
        "KinesisFirehoseOutput": {
          "$ref": "#/$defs/KinesisFirehoseOutput"
        },
        "KinesisStreamsOutput": {
          "$ref": "#/$defs/KinesisStreamsOutput"
        },
        "Name": {
          "oneOf": [
            {
              "type": "string"
            },
            {
              "$ref": "https://catalog.lintel.tools/schemas/schemastore/serverless-framework-configuration/_shared/latest--cf.functions.json#/Aws_CF_FunctionString"
            }
          ]
        }
      },
      "required": [
        "DestinationSchema"
      ],
      "title": "AWSKinesisAnalyticsApplicationOutputOutputDefinition"
    },
    "KinesisStreamsOutput": {
      "type": "object",
      "additionalProperties": false,
      "properties": {
        "ResourceARN": {
          "oneOf": [
            {
              "type": "string"
            },
            {
              "$ref": "https://catalog.lintel.tools/schemas/schemastore/serverless-framework-configuration/_shared/latest--cf.functions.json#/Aws_CF_FunctionString"
            }
          ]
        },
        "RoleARN": {
          "oneOf": [
            {
              "type": "string"
            },
            {
              "$ref": "https://catalog.lintel.tools/schemas/schemastore/serverless-framework-configuration/_shared/latest--cf.functions.json#/Aws_CF_FunctionString"
            }
          ]
        }
      },
      "required": [
        "ResourceARN",
        "RoleARN"
      ],
      "title": "AWSKinesisAnalyticsApplicationOutputKinesisStreamsOutputDefinition"
    },
    "KinesisFirehoseOutput": {
      "type": "object",
      "additionalProperties": false,
      "properties": {
        "ResourceARN": {
          "oneOf": [
            {
              "type": "string"
            },
            {
              "$ref": "https://catalog.lintel.tools/schemas/schemastore/serverless-framework-configuration/_shared/latest--cf.functions.json#/Aws_CF_FunctionString"
            }
          ]
        },
        "RoleARN": {
          "oneOf": [
            {
              "type": "string"
            },
            {
              "$ref": "https://catalog.lintel.tools/schemas/schemastore/serverless-framework-configuration/_shared/latest--cf.functions.json#/Aws_CF_FunctionString"
            }
          ]
        }
      },
      "required": [
        "ResourceARN",
        "RoleARN"
      ],
      "title": "AWSKinesisAnalyticsApplicationOutputKinesisFirehoseOutputDefinition"
    },
    "LambdaOutput": {
      "type": "object",
      "additionalProperties": false,
      "properties": {
        "ResourceARN": {
          "oneOf": [
            {
              "type": "string"
            },
            {
              "$ref": "https://catalog.lintel.tools/schemas/schemastore/serverless-framework-configuration/_shared/latest--cf.functions.json#/Aws_CF_FunctionString"
            }
          ]
        },
        "RoleARN": {
          "oneOf": [
            {
              "type": "string"
            },
            {
              "$ref": "https://catalog.lintel.tools/schemas/schemastore/serverless-framework-configuration/_shared/latest--cf.functions.json#/Aws_CF_FunctionString"
            }
          ]
        }
      },
      "required": [
        "ResourceARN",
        "RoleARN"
      ],
      "title": "AWSKinesisAnalyticsApplicationOutputLambdaOutputDefinition"
    },
    "DestinationSchema": {
      "type": "object",
      "additionalProperties": false,
      "properties": {
        "RecordFormatType": {
          "oneOf": [
            {
              "type": "string"
            },
            {
              "$ref": "https://catalog.lintel.tools/schemas/schemastore/serverless-framework-configuration/_shared/latest--cf.functions.json#/Aws_CF_FunctionString"
            }
          ]
        }
      },
      "title": "AWSKinesisAnalyticsApplicationOutputDestinationSchemaDefinition"
    }
  },
  "required": [
    "ApplicationName",
    "Output"
  ],
  "createOnlyProperties": [
    "/properties/ApplicationName"
  ]
}
